{"cameraMode":{"drawMode":0,"name":"Shaded","section":"Shading Mode"},"sceneLighting":true,"audioPlay":false,"sceneViewState":{"showFog":true,"showMaterialUpdate":false,"showSkybox":true,"showFlares":true,"showImageEffects":true,"showParticleSystems":true},"in2DMode":false,"pivot":{"x":-5.998594760894775,"y":-1.0768855810165406,"z":2.2507059574127199},"rotation":{"x":0.045280445367097858,"y":-0.022217433899641038,"z":0.000716713082510978,"w":0.9988381266593933},"size":9.490278244018555,"orthographic":false}